[{"dirName":"肥啾","fileName":"1.jpeg","iconID":"266.320 1.jpeg","extension":{"size":64,"offset":[0,0]}},{"dirName":"肥啾","fileName":"2.jpeg","iconID":"334.320 2.jpeg","extension":{"size":64,"offset":[0,0]}},{"dirName":"肥啾","fileName":"3.jpeg","iconID":"398.320 3.jpeg","extension":{"size":64,"offset":[0,0]}},{"dirName":"肥啾","fileName":"4.jpeg","iconID":"328.320 4.jpeg","extension":{"size":64,"offset":[0,0]}},{"dirName":"猫咪","fileName":"1.jpeg","iconID":"366.366 1.jpeg","extension":{"size":64,"offset":[0,0]}},{"dirName":"猫咪","fileName":"2.jpeg","iconID":"473.378 2.jpeg","extension":{"size":64,"offset":[0,0]}},{"dirName":"猫咪","fileName":"3.jpeg","iconID":"240.320 3.jpeg","extension":{"size":64,"offset":[0,0]}},{"dirName":"猫咪","fileName":"4.jpeg","iconID":"266.320 4.jpeg","extension":{"size":64,"offset":[0,0]}},{"dirName":"猫咪","fileName":"5.jpeg","iconID":"474.355 5.jpeg","extension":{"size":64,"offset":[0,0]}},{"dirName":"肥啾","fileName":"1.jpeg","iconID":"266.320 1.jpeg","extension":{"size":64,"offset":[0,0]}},{"dirName":"肥啾","fileName":"2.jpeg","iconID":"334.320 2.jpeg","extension":{"size":64,"offset":[0,0]}},{"dirName":"肥啾","fileName":"3.jpeg","iconID":"398.320 3.jpeg","extension":{"size":64,"offset":[0,0]}},{"dirName":"肥啾","fileName":"4.jpeg","iconID":"328.320 4.jpeg","extension":{"size":64,"offset":[0,0]}}]
